bismuth/__init__.py
bismuth/__main__.py
bismuthcli-0.4.11.dist-info/METADATA
bismuthcli-0.4.11.dist-info/WHEEL
bismuthcli-0.4.11.dist-info/RECORD
