Metadata-Version: 2.4
Name: bismuthcli
Version: 0.4.11
License-Expression: Apache-2.0
Requires-Dist: prompt-toolkit
Requires-Dist: requests
Requires-Dist: termcolor
